{
  "status": "ok",
  "data": [
    {
      "id": 1,
      "name": "Câmera De Vigilância Segurança Ip Wifi (Visão Noturna)",
      "price": 499.9,
      "url": "https://www.google.com/shopping/product/2318909396084813225?client=firefox-b-e&sca_esv=dcda4b761e7f6457&sxsrf=ADLYWIJic-yR_f0IGam2JUGn9IeBT1Dc7A:1731769313592&q=C%C3%A2meras+IP+de+alta+resolu%C3%A7%C3%A3o&biw=1366&bih=639&dpr=1&prds=eto:16872685470002854767_0,pid:13330856170447019731,rsk:PC_8189103200332939115&sa=X&ved=0ahUKEwi2_9-8j-GJAxUnBrkGHayiIo4Q8wIIhQw"
    }
  ]
}
